<simulation>
    <metadata>
        <type>Game of Life</type>
        <title>Spaceship</title>
        <author>Stitch</author>
        <description>uh. elvis.</description>
    </metadata>

    <grid rows="52" columns="60">
        <!-- Empty rows for centering -->
        <cell state="dead"/><cell state="dead"/><cell state="dead"/><cell state="dead"/><cell state="dead"/><cell state="dead"/><cell state="dead"/><cell state="dead"/><cell state="dead"/><cell state="dead"/><cell state="dead"/><cell state="dead"/><cell state="dead"/><cell state="dead"/><cell state="dead"/><cell state="dead"/><cell state="dead"/><cell state="dead"/><cell state="dead"/><cell state="dead"/><cell state="dead"/><cell state="dead"/><cell state="dead"/><cell state="dead"/><cell state="dead"/><cell state="dead"/><cell state="dead"/><cell state="dead"/><cell state="dead"/><cell state="dead"/><cell state="dead"/><cell state="dead"/><cell state="dead"/><cell state="dead"/><cell state="dead"/><cell state="dead"/><cell state="dead"/><cell state="dead"/><cell state="dead"/><cell state="dead"/><cell state="dead"/><cell state="dead"/><cell state="dead"/><cell state="dead"/><cell state="dead"/><cell state="dead"/><cell state="dead"/><cell state="dead"/><cell state="dead"/><cell state="dead"/><cell state="dead"/><cell state="dead"/><cell state="dead"/><cell state="dead"/><cell state="dead"/><cell state="dead"/><cell state="dead"/><cell state="dead"/><cell state="dead"/><cell state="dead"/>
        <cell state="dead"/><cell state="dead"/><cell state="dead"/><cell state="dead"/><cell state="dead"/><cell state="dead"/><cell state="dead"/><cell state="dead"/><cell state="dead"/><cell state="dead"/><cell state="dead"/><cell state="dead"/><cell state="dead"/><cell state="dead"/><cell state="dead"/><cell state="dead"/><cell state="dead"/><cell state="dead"/><cell state="dead"/><cell state="dead"/><cell state="dead"/><cell state="dead"/><cell state="dead"/><cell state="dead"/><cell state="dead"/><cell state="dead"/><cell state="dead"/><cell state="dead"/><cell state="dead"/><cell state="dead"/><cell state="dead"/><cell state="dead"/><cell state="dead"/><cell state="dead"/><cell state="dead"/><cell state="dead"/><cell state="dead"/><cell state="dead"/><cell state="dead"/><cell state="dead"/><cell state="dead"/><cell state="dead"/><cell state="dead"/><cell state="dead"/><cell state="dead"/><cell state="dead"/><cell state="dead"/><cell state="dead"/><cell state="dead"/><cell state="dead"/><cell state="dead"/><cell state="dead"/><cell state="dead"/><cell state="dead"/><cell state="dead"/><cell state="dead"/><cell state="dead"/><cell state="dead"/><cell state="dead"/><cell state="dead"/>
        <cell state="dead"/><cell state="dead"/><cell state="dead"/><cell state="dead"/><cell state="dead"/><cell state="dead"/><cell state="dead"/><cell state="dead"/><cell state="dead"/><cell state="dead"/><cell state="dead"/><cell state="dead"/><cell state="dead"/><cell state="dead"/><cell state="dead"/><cell state="dead"/><cell state="dead"/><cell state="dead"/><cell state="dead"/><cell state="dead"/><cell state="dead"/><cell state="dead"/><cell state="dead"/><cell state="dead"/><cell state="dead"/><cell state="dead"/><cell state="dead"/><cell state="dead"/><cell state="dead"/><cell state="dead"/><cell state="dead"/><cell state="dead"/><cell state="dead"/><cell state="dead"/><cell state="dead"/><cell state="dead"/><cell state="dead"/><cell state="dead"/><cell state="dead"/><cell state="dead"/><cell state="dead"/><cell state="dead"/><cell state="dead"/><cell state="dead"/><cell state="dead"/><cell state="dead"/><cell state="dead"/><cell state="dead"/><cell state="dead"/><cell state="dead"/><cell state="dead"/><cell state="dead"/><cell state="dead"/><cell state="dead"/><cell state="dead"/><cell state="dead"/><cell state="dead"/><cell state="dead"/><cell state="dead"/><cell state="dead"/>
        <cell state="dead"/><cell state="dead"/><cell state="dead"/><cell state="dead"/><cell state="dead"/><cell state="dead"/><cell state="dead"/><cell state="dead"/><cell state="dead"/><cell state="dead"/><cell state="dead"/><cell state="dead"/><cell state="dead"/><cell state="dead"/><cell state="dead"/><cell state="dead"/><cell state="dead"/><cell state="dead"/><cell state="dead"/><cell state="dead"/><cell state="dead"/><cell state="dead"/><cell state="dead"/><cell state="dead"/><cell state="dead"/><cell state="dead"/><cell state="dead"/><cell state="dead"/><cell state="dead"/><cell state="dead"/><cell state="dead"/><cell state="dead"/><cell state="dead"/><cell state="dead"/><cell state="dead"/><cell state="dead"/><cell state="dead"/><cell state="dead"/><cell state="dead"/><cell state="dead"/><cell state="dead"/><cell state="dead"/><cell state="dead"/><cell state="dead"/><cell state="dead"/><cell state="dead"/><cell state="dead"/><cell state="dead"/><cell state="dead"/><cell state="dead"/><cell state="dead"/><cell state="dead"/><cell state="dead"/><cell state="dead"/><cell state="dead"/><cell state="dead"/><cell state="dead"/><cell state="dead"/><cell state="dead"/><cell state="dead"/>
        <cell state="dead"/><cell state="dead"/><cell state="dead"/><cell state="dead"/><cell state="dead"/><cell state="dead"/><cell state="dead"/><cell state="dead"/><cell state="dead"/><cell state="dead"/><cell state="dead"/><cell state="dead"/><cell state="dead"/><cell state="dead"/><cell state="dead"/><cell state="dead"/><cell state="dead"/><cell state="dead"/><cell state="dead"/><cell state="dead"/><cell state="dead"/><cell state="dead"/><cell state="dead"/><cell state="dead"/><cell state="dead"/><cell state="dead"/><cell state="dead"/><cell state="dead"/><cell state="dead"/><cell state="dead"/><cell state="dead"/><cell state="dead"/><cell state="dead"/><cell state="dead"/><cell state="dead"/><cell state="dead"/><cell state="dead"/><cell state="dead"/><cell state="dead"/><cell state="dead"/><cell state="dead"/><cell state="dead"/><cell state="dead"/><cell state="dead"/><cell state="dead"/><cell state="dead"/><cell state="dead"/><cell state="dead"/><cell state="dead"/><cell state="dead"/><cell state="dead"/><cell state="dead"/><cell state="dead"/><cell state="dead"/><cell state="dead"/><cell state="dead"/><cell state="dead"/><cell state="dead"/><cell state="dead"/><cell state="dead"/>
        <cell state="dead"/><cell state="dead"/><cell state="dead"/><cell state="dead"/><cell state="dead"/><cell state="dead"/><cell state="dead"/><cell state="dead"/><cell state="dead"/><cell state="dead"/><cell state="dead"/><cell state="dead"/><cell state="dead"/><cell state="dead"/><cell state="dead"/><cell state="dead"/><cell state="dead"/><cell state="dead"/><cell state="dead"/><cell state="dead"/><cell state="dead"/><cell state="dead"/><cell state="dead"/><cell state="dead"/><cell state="dead"/><cell state="dead"/><cell state="dead"/><cell state="dead"/><cell state="dead"/><cell state="dead"/><cell state="dead"/><cell state="dead"/><cell state="dead"/><cell state="dead"/><cell state="dead"/><cell state="dead"/><cell state="dead"/><cell state="dead"/><cell state="dead"/><cell state="dead"/><cell state="dead"/><cell state="dead"/><cell state="dead"/><cell state="dead"/><cell state="dead"/><cell state="dead"/><cell state="dead"/><cell state="dead"/><cell state="dead"/><cell state="dead"/><cell state="dead"/><cell state="dead"/><cell state="dead"/><cell state="dead"/><cell state="dead"/><cell state="dead"/><cell state="dead"/><cell state="dead"/><cell state="dead"/><cell state="dead"/>
        <cell state="dead"/><cell state="dead"/><cell state="dead"/><cell state="dead"/><cell state="dead"/><cell state="dead"/><cell state="dead"/><cell state="dead"/><cell state="dead"/><cell state="dead"/><cell state="dead"/><cell state="dead"/><cell state="dead"/><cell state="dead"/><cell state="dead"/><cell state="dead"/><cell state="dead"/><cell state="dead"/><cell state="dead"/><cell state="dead"/><cell state="dead"/><cell state="dead"/><cell state="dead"/><cell state="dead"/><cell state="dead"/><cell state="dead"/><cell state="dead"/><cell state="dead"/><cell state="dead"/><cell state="dead"/><cell state="dead"/><cell state="dead"/><cell state="dead"/><cell state="dead"/><cell state="dead"/><cell state="dead"/><cell state="dead"/><cell state="dead"/><cell state="dead"/><cell state="dead"/><cell state="dead"/><cell state="dead"/><cell state="dead"/><cell state="dead"/><cell state="dead"/><cell state="dead"/><cell state="dead"/><cell state="dead"/><cell state="dead"/><cell state="dead"/><cell state="dead"/><cell state="dead"/><cell state="dead"/><cell state="dead"/><cell state="dead"/><cell state="dead"/><cell state="dead"/><cell state="dead"/><cell state="dead"/><cell state="dead"/>
        <cell state="dead"/><cell state="dead"/><cell state="dead"/><cell state="dead"/><cell state="dead"/><cell state="dead"/><cell state="dead"/><cell state="dead"/><cell state="dead"/><cell state="dead"/><cell state="dead"/><cell state="dead"/><cell state="dead"/><cell state="dead"/><cell state="dead"/><cell state="dead"/><cell state="dead"/><cell state="dead"/><cell state="dead"/><cell state="dead"/><cell state="dead"/><cell state="dead"/><cell state="dead"/><cell state="dead"/><cell state="dead"/><cell state="dead"/><cell state="dead"/><cell state="dead"/><cell state="dead"/><cell state="dead"/><cell state="dead"/><cell state="dead"/><cell state="dead"/><cell state="dead"/><cell state="dead"/><cell state="dead"/><cell state="dead"/><cell state="dead"/><cell state="dead"/><cell state="dead"/><cell state="dead"/><cell state="dead"/><cell state="dead"/><cell state="dead"/><cell state="dead"/><cell state="dead"/><cell state="dead"/><cell state="dead"/><cell state="dead"/><cell state="dead"/><cell state="dead"/><cell state="dead"/><cell state="dead"/><cell state="dead"/><cell state="dead"/><cell state="dead"/><cell state="dead"/><cell state="dead"/><cell state="dead"/><cell state="dead"/>
        <cell state="dead"/><cell state="dead"/><cell state="dead"/><cell state="dead"/><cell state="dead"/><cell state="dead"/><cell state="dead"/><cell state="dead"/><cell state="dead"/><cell state="dead"/><cell state="dead"/><cell state="dead"/><cell state="dead"/><cell state="dead"/><cell state="dead"/><cell state="dead"/><cell state="dead"/><cell state="dead"/><cell state="dead"/><cell state="dead"/><cell state="dead"/><cell state="dead"/><cell state="dead"/><cell state="dead"/><cell state="dead"/><cell state="dead"/><cell state="dead"/><cell state="dead"/><cell state="dead"/><cell state="dead"/><cell state="dead"/><cell state="dead"/><cell state="dead"/><cell state="dead"/><cell state="dead"/><cell state="dead"/><cell state="dead"/><cell state="dead"/><cell state="dead"/><cell state="dead"/><cell state="dead"/><cell state="dead"/><cell state="dead"/><cell state="dead"/><cell state="dead"/><cell state="dead"/><cell state="dead"/><cell state="dead"/><cell state="dead"/><cell state="dead"/><cell state="dead"/><cell state="dead"/><cell state="dead"/><cell state="dead"/><cell state="dead"/><cell state="dead"/><cell state="dead"/><cell state="dead"/><cell state="dead"/><cell state="dead"/>
        <cell state="dead"/><cell state="dead"/><cell state="dead"/><cell state="dead"/><cell state="dead"/><cell state="dead"/><cell state="dead"/><cell state="dead"/><cell state="dead"/><cell state="dead"/><cell state="dead"/><cell state="dead"/><cell state="dead"/><cell state="dead"/><cell state="dead"/><cell state="dead"/><cell state="dead"/><cell state="dead"/><cell state="dead"/><cell state="dead"/><cell state="dead"/><cell state="dead"/><cell state="dead"/><cell state="dead"/><cell state="dead"/><cell state="dead"/><cell state="dead"/><cell state="dead"/><cell state="dead"/><cell state="dead"/><cell state="dead"/><cell state="dead"/><cell state="dead"/><cell state="dead"/><cell state="dead"/><cell state="dead"/><cell state="dead"/><cell state="dead"/><cell state="dead"/><cell state="dead"/><cell state="dead"/><cell state="dead"/><cell state="dead"/><cell state="dead"/><cell state="dead"/><cell state="dead"/><cell state="dead"/><cell state="dead"/><cell state="dead"/><cell state="dead"/><cell state="dead"/><cell state="dead"/><cell state="dead"/><cell state="dead"/><cell state="dead"/><cell state="dead"/><cell state="dead"/><cell state="dead"/><cell state="dead"/><cell state="dead"/>
        <cell state="dead"/><cell state="dead"/><cell state="dead"/><cell state="dead"/><cell state="dead"/><cell state="dead"/><cell state="dead"/><cell state="dead"/><cell state="dead"/><cell state="dead"/><cell state="dead"/><cell state="dead"/><cell state="dead"/><cell state="dead"/><cell state="dead"/><cell state="dead"/><cell state="dead"/><cell state="dead"/><cell state="dead"/><cell state="dead"/><cell state="dead"/><cell state="dead"/><cell state="dead"/><cell state="dead"/><cell state="dead"/><cell state="dead"/><cell state="dead"/><cell state="dead"/><cell state="dead"/><cell state="dead"/><cell state="dead"/><cell state="dead"/><cell state="dead"/><cell state="dead"/><cell state="dead"/><cell state="dead"/><cell state="dead"/><cell state="dead"/><cell state="dead"/><cell state="dead"/><cell state="dead"/><cell state="dead"/><cell state="dead"/><cell state="dead"/><cell state="dead"/><cell state="dead"/><cell state="dead"/><cell state="dead"/><cell state="dead"/><cell state="dead"/><cell state="dead"/><cell state="dead"/><cell state="dead"/><cell state="dead"/><cell state="dead"/><cell state="dead"/><cell state="dead"/><cell state="dead"/><cell state="dead"/><cell state="dead"/>
        <cell state="dead"/><cell state="dead"/><cell state="dead"/><cell state="dead"/><cell state="dead"/><cell state="dead"/><cell state="dead"/><cell state="dead"/><cell state="dead"/><cell state="dead"/><cell state="dead"/><cell state="dead"/><cell state="dead"/><cell state="dead"/><cell state="dead"/><cell state="dead"/><cell state="dead"/><cell state="dead"/><cell state="dead"/><cell state="dead"/><cell state="dead"/><cell state="dead"/><cell state="dead"/><cell state="dead"/><cell state="dead"/><cell state="dead"/><cell state="dead"/><cell state="dead"/><cell state="dead"/><cell state="dead"/><cell state="dead"/><cell state="dead"/><cell state="dead"/><cell state="dead"/><cell state="dead"/><cell state="dead"/><cell state="dead"/><cell state="dead"/><cell state="dead"/><cell state="dead"/><cell state="dead"/><cell state="dead"/><cell state="dead"/><cell state="dead"/><cell state="dead"/><cell state="dead"/><cell state="dead"/><cell state="dead"/><cell state="dead"/><cell state="dead"/><cell state="dead"/><cell state="dead"/><cell state="dead"/><cell state="dead"/><cell state="dead"/><cell state="dead"/><cell state="dead"/><cell state="dead"/><cell state="dead"/><cell state="dead"/>
        <cell state="dead"/><cell state="dead"/><cell state="dead"/><cell state="dead"/><cell state="dead"/><cell state="dead"/><cell state="dead"/><cell state="dead"/><cell state="dead"/><cell state="dead"/><cell state="dead"/><cell state="dead"/><cell state="dead"/><cell state="dead"/><cell state="dead"/><cell state="dead"/><cell state="dead"/><cell state="dead"/><cell state="dead"/><cell state="dead"/><cell state="dead"/><cell state="dead"/><cell state="dead"/><cell state="dead"/><cell state="dead"/><cell state="dead"/><cell state="dead"/><cell state="dead"/><cell state="dead"/><cell state="dead"/><cell state="dead"/><cell state="dead"/><cell state="dead"/><cell state="dead"/><cell state="dead"/><cell state="dead"/><cell state="dead"/><cell state="dead"/><cell state="dead"/><cell state="dead"/><cell state="dead"/><cell state="dead"/><cell state="dead"/><cell state="dead"/><cell state="dead"/><cell state="dead"/><cell state="dead"/><cell state="dead"/><cell state="dead"/><cell state="dead"/><cell state="dead"/><cell state="dead"/><cell state="dead"/><cell state="dead"/><cell state="dead"/><cell state="dead"/><cell state="dead"/><cell state="dead"/><cell state="dead"/><cell state="dead"/>
        <cell state="dead"/><cell state="dead"/><cell state="dead"/><cell state="dead"/><cell state="dead"/><cell state="dead"/><cell state="dead"/><cell state="dead"/><cell state="dead"/><cell state="dead"/><cell state="dead"/><cell state="dead"/><cell state="dead"/><cell state="dead"/><cell state="dead"/><cell state="dead"/><cell state="dead"/><cell state="dead"/><cell state="dead"/><cell state="dead"/><cell state="dead"/><cell state="dead"/><cell state="dead"/><cell state="dead"/><cell state="dead"/><cell state="dead"/><cell state="dead"/><cell state="dead"/><cell state="dead"/><cell state="dead"/><cell state="dead"/><cell state="dead"/><cell state="dead"/><cell state="dead"/><cell state="dead"/><cell state="dead"/><cell state="dead"/><cell state="dead"/><cell state="dead"/><cell state="dead"/><cell state="dead"/><cell state="dead"/><cell state="dead"/><cell state="dead"/><cell state="dead"/><cell state="dead"/><cell state="dead"/><cell state="dead"/><cell state="dead"/><cell state="dead"/><cell state="dead"/><cell state="dead"/><cell state="dead"/><cell state="dead"/><cell state="dead"/><cell state="dead"/><cell state="dead"/><cell state="dead"/><cell state="dead"/><cell state="dead"/>
        <cell state="dead"/><cell state="dead"/><cell state="dead"/><cell state="dead"/><cell state="dead"/><cell state="dead"/><cell state="dead"/><cell state="dead"/><cell state="dead"/><cell state="dead"/><cell state="dead"/><cell state="dead"/><cell state="dead"/><cell state="dead"/><cell state="dead"/><cell state="dead"/><cell state="dead"/><cell state="dead"/><cell state="dead"/><cell state="dead"/><cell state="dead"/><cell state="dead"/><cell state="dead"/><cell state="dead"/><cell state="dead"/><cell state="dead"/><cell state="dead"/><cell state="dead"/><cell state="dead"/><cell state="dead"/><cell state="dead"/><cell state="dead"/><cell state="dead"/><cell state="dead"/><cell state="dead"/><cell state="dead"/><cell state="dead"/><cell state="dead"/><cell state="dead"/><cell state="dead"/><cell state="dead"/><cell state="dead"/><cell state="dead"/><cell state="dead"/><cell state="dead"/><cell state="dead"/><cell state="dead"/><cell state="dead"/><cell state="dead"/><cell state="dead"/><cell state="dead"/><cell state="dead"/><cell state="dead"/><cell state="dead"/><cell state="dead"/><cell state="dead"/><cell state="dead"/><cell state="dead"/><cell state="dead"/><cell state="dead"/>
        <cell state="dead"/><cell state="dead"/><cell state="dead"/><cell state="dead"/><cell state="dead"/><cell state="dead"/><cell state="dead"/><cell state="dead"/><cell state="dead"/><cell state="dead"/><cell state="dead"/><cell state="dead"/><cell state="dead"/><cell state="dead"/><cell state="dead"/><cell state="dead"/><cell state="dead"/><cell state="dead"/><cell state="dead"/><cell state="dead"/><cell state="dead"/><cell state="dead"/><cell state="dead"/><cell state="dead"/><cell state="dead"/><cell state="dead"/><cell state="dead"/><cell state="dead"/><cell state="dead"/><cell state="dead"/><cell state="dead"/><cell state="dead"/><cell state="dead"/><cell state="dead"/><cell state="dead"/><cell state="dead"/><cell state="dead"/><cell state="dead"/><cell state="dead"/><cell state="dead"/><cell state="dead"/><cell state="dead"/><cell state="dead"/><cell state="dead"/><cell state="dead"/><cell state="dead"/><cell state="dead"/><cell state="dead"/><cell state="dead"/><cell state="dead"/><cell state="dead"/><cell state="dead"/><cell state="dead"/><cell state="dead"/><cell state="dead"/><cell state="dead"/><cell state="dead"/><cell state="dead"/><cell state="dead"/><cell state="dead"/>
        <cell state="dead"/><cell state="dead"/><cell state="dead"/><cell state="dead"/><cell state="dead"/><cell state="dead"/><cell state="dead"/><cell state="dead"/><cell state="dead"/><cell state="dead"/><cell state="dead"/><cell state="dead"/><cell state="dead"/><cell state="dead"/><cell state="dead"/><cell state="dead"/><cell state="dead"/><cell state="dead"/><cell state="dead"/><cell state="dead"/><cell state="dead"/><cell state="dead"/><cell state="dead"/><cell state="dead"/><cell state="dead"/><cell state="dead"/><cell state="dead"/><cell state="dead"/><cell state="dead"/><cell state="dead"/><cell state="dead"/><cell state="dead"/><cell state="dead"/><cell state="dead"/><cell state="dead"/><cell state="dead"/><cell state="dead"/><cell state="dead"/><cell state="dead"/><cell state="dead"/><cell state="dead"/><cell state="dead"/><cell state="dead"/><cell state="dead"/><cell state="dead"/><cell state="dead"/><cell state="dead"/><cell state="dead"/><cell state="dead"/><cell state="dead"/><cell state="dead"/><cell state="dead"/><cell state="dead"/><cell state="dead"/><cell state="dead"/><cell state="dead"/><cell state="dead"/><cell state="dead"/><cell state="dead"/><cell state="dead"/>
        <cell state="dead"/><cell state="dead"/><cell state="dead"/><cell state="dead"/><cell state="dead"/><cell state="dead"/><cell state="dead"/><cell state="dead"/><cell state="dead"/><cell state="dead"/><cell state="dead"/><cell state="dead"/><cell state="dead"/><cell state="dead"/><cell state="dead"/><cell state="dead"/><cell state="dead"/><cell state="dead"/><cell state="dead"/><cell state="dead"/><cell state="dead"/><cell state="dead"/><cell state="dead"/><cell state="dead"/><cell state="dead"/><cell state="dead"/><cell state="dead"/><cell state="dead"/><cell state="dead"/><cell state="dead"/><cell state="dead"/><cell state="dead"/><cell state="dead"/><cell state="dead"/><cell state="dead"/><cell state="dead"/><cell state="dead"/><cell state="dead"/><cell state="dead"/><cell state="dead"/><cell state="dead"/><cell state="dead"/><cell state="dead"/><cell state="dead"/><cell state="dead"/><cell state="dead"/><cell state="dead"/><cell state="dead"/><cell state="dead"/><cell state="dead"/><cell state="dead"/><cell state="dead"/><cell state="dead"/><cell state="dead"/><cell state="dead"/><cell state="dead"/><cell state="dead"/><cell state="dead"/><cell state="dead"/><cell state="dead"/>

        <!-- Hammerhead pattern -->
        <cell state="dead"/><cell state="dead"/><cell state="dead"/><cell state="dead"/><cell state="dead"/><cell state="dead"/><cell state="dead"/><cell state="dead"/><cell state="dead"/><cell state="dead"/><cell state="dead"/><cell state="dead"/><cell state="dead"/><cell state="dead"/><cell state="dead"/><cell state="dead"/><cell state="dead"/><cell state="dead"/><cell state="dead"/><cell state="dead"/><cell state="dead"/><cell state="dead"/><cell state="dead"/><cell state="dead"/><cell state="dead"/><cell state="dead"/><cell state="dead"/><cell state="dead"/><cell state="dead"/><cell state="dead"/><cell state="alive"/><cell state="alive"/><cell state="alive"/><cell state="alive"/><cell state="alive"/><cell state="dead"/><cell state="dead"/><cell state="dead"/><cell state="dead"/><cell state="dead"/><cell state="dead"/><cell state="dead"/><cell state="dead"/><cell state="dead"/><cell state="dead"/><cell state="dead"/><cell state="dead"/><cell state="dead"/><cell state="dead"/><cell state="dead"/><cell state="dead"/><cell state="dead"/><cell state="dead"/><cell state="dead"/><cell state="dead"/><cell state="dead"/><cell state="dead"/><cell state="dead"/><cell state="dead"/><cell state="dead"/>
        <cell state="dead"/><cell state="dead"/><cell state="dead"/><cell state="dead"/><cell state="dead"/><cell state="dead"/><cell state="dead"/><cell state="dead"/><cell state="dead"/><cell state="dead"/><cell state="dead"/><cell state="dead"/><cell state="dead"/><cell state="dead"/><cell state="dead"/><cell state="dead"/><cell state="dead"/><cell state="dead"/><cell state="dead"/><cell state="dead"/><cell state="dead"/><cell state="dead"/><cell state="dead"/><cell state="dead"/><cell state="dead"/><cell state="dead"/><cell state="dead"/><cell state="dead"/><cell state="dead"/><cell state="dead"/><cell state="alive"/><cell state="dead"/><cell state="dead"/><cell state="dead"/><cell state="alive"/><cell state="dead"/><cell state="dead"/><cell state="dead"/><cell state="dead"/><cell state="dead"/><cell state="dead"/><cell state="alive"/><cell state="alive"/><cell state="dead"/><cell state="dead"/><cell state="dead"/><cell state="dead"/><cell state="dead"/><cell state="dead"/><cell state="dead"/><cell state="dead"/><cell state="dead"/><cell state="dead"/><cell state="dead"/><cell state="dead"/><cell state="dead"/><cell state="dead"/><cell state="dead"/><cell state="dead"/><cell state="dead"/>
        <cell state="dead"/><cell state="dead"/><cell state="dead"/><cell state="dead"/><cell state="dead"/><cell state="dead"/><cell state="dead"/><cell state="dead"/><cell state="dead"/><cell state="dead"/><cell state="dead"/><cell state="dead"/><cell state="dead"/><cell state="dead"/><cell state="dead"/><cell state="dead"/><cell state="dead"/><cell state="dead"/><cell state="dead"/><cell state="dead"/><cell state="dead"/><cell state="dead"/><cell state="dead"/><cell state="dead"/><cell state="dead"/><cell state="dead"/><cell state="dead"/><cell state="dead"/><cell state="dead"/><cell state="dead"/><cell state="alive"/><cell state="dead"/><cell state="dead"/><cell state="dead"/><cell state="dead"/><cell state="dead"/><cell state="dead"/><cell state="dead"/><cell state="dead"/><cell state="dead"/><cell state="alive"/><cell state="alive"/><cell state="dead"/><cell state="alive"/><cell state="alive"/><cell state="alive"/><cell state="dead"/><cell state="dead"/><cell state="dead"/><cell state="dead"/><cell state="dead"/><cell state="dead"/><cell state="dead"/><cell state="dead"/><cell state="dead"/><cell state="dead"/><cell state="dead"/><cell state="dead"/><cell state="dead"/><cell state="dead"/>
        <cell state="dead"/><cell state="dead"/><cell state="dead"/><cell state="dead"/><cell state="dead"/><cell state="dead"/><cell state="dead"/><cell state="dead"/><cell state="dead"/><cell state="dead"/><cell state="dead"/><cell state="dead"/><cell state="dead"/><cell state="dead"/><cell state="dead"/><cell state="dead"/><cell state="dead"/><cell state="dead"/><cell state="dead"/><cell state="dead"/><cell state="dead"/><cell state="dead"/><cell state="dead"/><cell state="dead"/><cell state="dead"/><cell state="dead"/><cell state="dead"/><cell state="dead"/><cell state="dead"/><cell state="dead"/><cell state="dead"/><cell state="alive"/><cell state="dead"/><cell state="dead"/><cell state="dead"/><cell state="dead"/><cell state="dead"/><cell state="dead"/><cell state="dead"/><cell state="alive"/><cell state="alive"/><cell state="dead"/><cell state="alive"/><cell state="alive"/><cell state="alive"/><cell state="alive"/><cell state="dead"/><cell state="dead"/><cell state="dead"/><cell state="dead"/><cell state="dead"/><cell state="dead"/><cell state="dead"/><cell state="dead"/><cell state="dead"/><cell state="dead"/><cell state="dead"/><cell state="dead"/><cell state="dead"/><cell state="dead"/>
        <cell state="dead"/><cell state="dead"/><cell state="dead"/><cell state="dead"/><cell state="dead"/><cell state="dead"/><cell state="dead"/><cell state="dead"/><cell state="dead"/><cell state="dead"/><cell state="dead"/><cell state="dead"/><cell state="dead"/><cell state="dead"/><cell state="dead"/><cell state="dead"/><cell state="dead"/><cell state="dead"/><cell state="dead"/><cell state="dead"/><cell state="dead"/><cell state="dead"/><cell state="dead"/><cell state="dead"/><cell state="dead"/><cell state="dead"/><cell state="dead"/><cell state="dead"/><cell state="dead"/><cell state="dead"/><cell state="dead"/><cell state="dead"/><cell state="dead"/><cell state="alive"/><cell state="alive"/><cell state="dead"/><cell state="dead"/><cell state="dead"/><cell state="alive"/><cell state="alive"/><cell state="dead"/><cell state="alive"/><cell state="dead"/><cell state="alive"/><cell state="alive"/><cell state="dead"/><cell state="alive"/><cell state="alive"/><cell state="dead"/><cell state="dead"/><cell state="dead"/><cell state="dead"/><cell state="dead"/><cell state="dead"/><cell state="dead"/><cell state="dead"/><cell state="dead"/><cell state="dead"/><cell state="dead"/><cell state="dead"/>
        <cell state="dead"/><cell state="dead"/><cell state="dead"/><cell state="dead"/><cell state="dead"/><cell state="dead"/><cell state="dead"/><cell state="dead"/><cell state="dead"/><cell state="dead"/><cell state="dead"/><cell state="dead"/><cell state="dead"/><cell state="dead"/><cell state="dead"/><cell state="dead"/><cell state="dead"/><cell state="dead"/><cell state="dead"/><cell state="dead"/><cell state="dead"/><cell state="dead"/><cell state="dead"/><cell state="dead"/><cell state="dead"/><cell state="dead"/><cell state="dead"/><cell state="dead"/><cell state="dead"/><cell state="dead"/><cell state="dead"/><cell state="dead"/><cell state="dead"/><cell state="dead"/><cell state="dead"/><cell state="alive"/><cell state="dead"/><cell state="dead"/><cell state="dead"/><cell state="alive"/><cell state="dead"/><cell state="alive"/><cell state="alive"/><cell state="dead"/><cell state="dead"/><cell state="dead"/><cell state="dead"/><cell state="dead"/><cell state="dead"/><cell state="dead"/><cell state="dead"/><cell state="dead"/><cell state="dead"/><cell state="dead"/><cell state="dead"/><cell state="dead"/><cell state="dead"/><cell state="dead"/><cell state="dead"/><cell state="dead"/>
        <cell state="dead"/><cell state="dead"/><cell state="dead"/><cell state="dead"/><cell state="dead"/><cell state="dead"/><cell state="dead"/><cell state="dead"/><cell state="dead"/><cell state="dead"/><cell state="dead"/><cell state="dead"/><cell state="dead"/><cell state="dead"/><cell state="dead"/><cell state="dead"/><cell state="dead"/><cell state="dead"/><cell state="dead"/><cell state="dead"/><cell state="dead"/><cell state="dead"/><cell state="dead"/><cell state="dead"/><cell state="dead"/><cell state="dead"/><cell state="dead"/><cell state="dead"/><cell state="dead"/><cell state="dead"/><cell state="dead"/><cell state="dead"/><cell state="dead"/><cell state="dead"/><cell state="dead"/><cell state="alive"/><cell state="dead"/><cell state="alive"/><cell state="dead"/><cell state="alive"/><cell state="dead"/><cell state="alive"/><cell state="dead"/><cell state="alive"/><cell state="dead"/><cell state="dead"/><cell state="dead"/><cell state="dead"/><cell state="dead"/><cell state="dead"/><cell state="dead"/><cell state="dead"/><cell state="dead"/><cell state="dead"/><cell state="dead"/><cell state="dead"/><cell state="dead"/><cell state="dead"/><cell state="dead"/><cell state="dead"/>
        <cell state="dead"/><cell state="dead"/><cell state="dead"/><cell state="dead"/><cell state="dead"/><cell state="dead"/><cell state="dead"/><cell state="dead"/><cell state="dead"/><cell state="dead"/><cell state="dead"/><cell state="dead"/><cell state="dead"/><cell state="dead"/><cell state="dead"/><cell state="dead"/><cell state="dead"/><cell state="dead"/><cell state="dead"/><cell state="dead"/><cell state="dead"/><cell state="dead"/><cell state="dead"/><cell state="dead"/><cell state="dead"/><cell state="dead"/><cell state="dead"/><cell state="dead"/><cell state="dead"/><cell state="dead"/><cell state="dead"/><cell state="dead"/><cell state="dead"/><cell state="dead"/><cell state="dead"/><cell state="dead"/><cell state="alive"/><cell state="dead"/><cell state="dead"/><cell state="dead"/><cell state="dead"/><cell state="dead"/><cell state="dead"/><cell state="dead"/><cell state="dead"/><cell state="dead"/><cell state="dead"/><cell state="dead"/><cell state="dead"/><cell state="dead"/><cell state="dead"/><cell state="dead"/><cell state="dead"/><cell state="dead"/><cell state="dead"/><cell state="dead"/><cell state="dead"/><cell state="dead"/><cell state="dead"/><cell state="dead"/>

        <cell state="dead"/><cell state="dead"/><cell state="dead"/><cell state="dead"/><cell state="dead"/><cell state="dead"/><cell state="dead"/><cell state="dead"/><cell state="dead"/><cell state="dead"/><cell state="dead"/><cell state="dead"/><cell state="dead"/><cell state="dead"/><cell state="dead"/><cell state="dead"/><cell state="dead"/><cell state="dead"/><cell state="dead"/><cell state="dead"/><cell state="dead"/><cell state="dead"/><cell state="dead"/><cell state="dead"/><cell state="dead"/><cell state="dead"/><cell state="dead"/><cell state="dead"/><cell state="dead"/><cell state="dead"/><cell state="dead"/><cell state="dead"/><cell state="dead"/><cell state="dead"/><cell state="dead"/><cell state="dead"/><cell state="alive"/><cell state="dead"/><cell state="dead"/><cell state="dead"/><cell state="dead"/><cell state="dead"/><cell state="dead"/><cell state="dead"/><cell state="dead"/><cell state="dead"/><cell state="dead"/><cell state="dead"/><cell state="dead"/><cell state="dead"/><cell state="dead"/><cell state="dead"/><cell state="dead"/><cell state="dead"/><cell state="dead"/><cell state="dead"/><cell state="dead"/><cell state="dead"/><cell state="dead"/><cell state="dead"/>
        <cell state="dead"/><cell state="dead"/><cell state="dead"/><cell state="dead"/><cell state="dead"/><cell state="dead"/><cell state="dead"/><cell state="dead"/><cell state="dead"/><cell state="dead"/><cell state="dead"/><cell state="dead"/><cell state="dead"/><cell state="dead"/><cell state="dead"/><cell state="dead"/><cell state="dead"/><cell state="dead"/><cell state="dead"/><cell state="dead"/><cell state="dead"/><cell state="dead"/><cell state="dead"/><cell state="dead"/><cell state="dead"/><cell state="dead"/><cell state="dead"/><cell state="dead"/><cell state="dead"/><cell state="dead"/><cell state="dead"/><cell state="dead"/><cell state="dead"/><cell state="dead"/><cell state="dead"/><cell state="alive"/><cell state="dead"/><cell state="alive"/><cell state="dead"/><cell state="alive"/><cell state="dead"/><cell state="alive"/><cell state="dead"/><cell state="alive"/><cell state="dead"/><cell state="dead"/><cell state="dead"/><cell state="dead"/><cell state="dead"/><cell state="dead"/><cell state="dead"/><cell state="dead"/><cell state="dead"/><cell state="dead"/><cell state="dead"/><cell state="dead"/><cell state="dead"/><cell state="dead"/><cell state="dead"/><cell state="dead"/>
        <cell state="dead"/><cell state="dead"/><cell state="dead"/><cell state="dead"/><cell state="dead"/><cell state="dead"/><cell state="dead"/><cell state="dead"/><cell state="dead"/><cell state="dead"/><cell state="dead"/><cell state="dead"/><cell state="dead"/><cell state="dead"/><cell state="dead"/><cell state="dead"/><cell state="dead"/><cell state="dead"/><cell state="dead"/><cell state="dead"/><cell state="dead"/><cell state="dead"/><cell state="dead"/><cell state="dead"/><cell state="dead"/><cell state="dead"/><cell state="dead"/><cell state="dead"/><cell state="dead"/><cell state="dead"/><cell state="dead"/><cell state="dead"/><cell state="dead"/><cell state="dead"/><cell state="dead"/><cell state="alive"/><cell state="dead"/><cell state="dead"/><cell state="dead"/><cell state="alive"/><cell state="dead"/><cell state="alive"/><cell state="alive"/><cell state="dead"/><cell state="dead"/><cell state="dead"/><cell state="dead"/><cell state="dead"/><cell state="dead"/><cell state="dead"/><cell state="dead"/><cell state="dead"/><cell state="dead"/><cell state="dead"/><cell state="dead"/><cell state="dead"/><cell state="dead"/><cell state="dead"/><cell state="dead"/><cell state="dead"/>
        <cell state="dead"/><cell state="dead"/><cell state="dead"/><cell state="dead"/><cell state="dead"/><cell state="dead"/><cell state="dead"/><cell state="dead"/><cell state="dead"/><cell state="dead"/><cell state="dead"/><cell state="dead"/><cell state="dead"/><cell state="dead"/><cell state="dead"/><cell state="dead"/><cell state="dead"/><cell state="dead"/><cell state="dead"/><cell state="dead"/><cell state="dead"/><cell state="dead"/><cell state="dead"/><cell state="dead"/><cell state="dead"/><cell state="dead"/><cell state="dead"/><cell state="dead"/><cell state="dead"/><cell state="dead"/><cell state="dead"/><cell state="dead"/><cell state="dead"/><cell state="alive"/><cell state="alive"/><cell state="dead"/><cell state="dead"/><cell state="dead"/><cell state="alive"/><cell state="alive"/><cell state="dead"/><cell state="alive"/><cell state="dead"/><cell state="alive"/><cell state="alive"/><cell state="dead"/><cell state="alive"/><cell state="alive"/><cell state="dead"/><cell state="dead"/><cell state="dead"/><cell state="dead"/><cell state="dead"/><cell state="dead"/><cell state="dead"/><cell state="dead"/><cell state="dead"/><cell state="dead"/><cell state="dead"/><cell state="dead"/>
        <cell state="dead"/><cell state="dead"/><cell state="dead"/><cell state="dead"/><cell state="dead"/><cell state="dead"/><cell state="dead"/><cell state="dead"/><cell state="dead"/><cell state="dead"/><cell state="dead"/><cell state="dead"/><cell state="dead"/><cell state="dead"/><cell state="dead"/><cell state="dead"/><cell state="dead"/><cell state="dead"/><cell state="dead"/><cell state="dead"/><cell state="dead"/><cell state="dead"/><cell state="dead"/><cell state="dead"/><cell state="dead"/><cell state="dead"/><cell state="dead"/><cell state="dead"/><cell state="dead"/><cell state="dead"/><cell state="dead"/><cell state="alive"/><cell state="dead"/><cell state="dead"/><cell state="dead"/><cell state="dead"/><cell state="dead"/><cell state="dead"/><cell state="dead"/><cell state="alive"/><cell state="alive"/><cell state="dead"/><cell state="alive"/><cell state="alive"/><cell state="alive"/><cell state="alive"/><cell state="dead"/><cell state="dead"/><cell state="dead"/><cell state="dead"/><cell state="dead"/><cell state="dead"/><cell state="dead"/><cell state="dead"/><cell state="dead"/><cell state="dead"/><cell state="dead"/><cell state="dead"/><cell state="dead"/><cell state="dead"/>
        <cell state="dead"/><cell state="dead"/><cell state="dead"/><cell state="dead"/><cell state="dead"/><cell state="dead"/><cell state="dead"/><cell state="dead"/><cell state="dead"/><cell state="dead"/><cell state="dead"/><cell state="dead"/><cell state="dead"/><cell state="dead"/><cell state="dead"/><cell state="dead"/><cell state="dead"/><cell state="dead"/><cell state="dead"/><cell state="dead"/><cell state="dead"/><cell state="dead"/><cell state="dead"/><cell state="dead"/><cell state="dead"/><cell state="dead"/><cell state="dead"/><cell state="dead"/><cell state="dead"/><cell state="dead"/><cell state="alive"/><cell state="dead"/><cell state="dead"/><cell state="dead"/><cell state="dead"/><cell state="dead"/><cell state="dead"/><cell state="dead"/><cell state="dead"/><cell state="dead"/><cell state="alive"/><cell state="alive"/><cell state="dead"/><cell state="alive"/><cell state="alive"/><cell state="alive"/><cell state="dead"/><cell state="dead"/><cell state="dead"/><cell state="dead"/><cell state="dead"/><cell state="dead"/><cell state="dead"/><cell state="dead"/><cell state="dead"/><cell state="dead"/><cell state="dead"/><cell state="dead"/><cell state="dead"/><cell state="dead"/>
        <cell state="dead"/><cell state="dead"/><cell state="dead"/><cell state="dead"/><cell state="dead"/><cell state="dead"/><cell state="dead"/><cell state="dead"/><cell state="dead"/><cell state="dead"/><cell state="dead"/><cell state="dead"/><cell state="dead"/><cell state="dead"/><cell state="dead"/><cell state="dead"/><cell state="dead"/><cell state="dead"/><cell state="dead"/><cell state="dead"/><cell state="dead"/><cell state="dead"/><cell state="dead"/><cell state="dead"/><cell state="dead"/><cell state="dead"/><cell state="dead"/><cell state="dead"/><cell state="dead"/><cell state="dead"/><cell state="alive"/><cell state="dead"/><cell state="dead"/><cell state="dead"/><cell state="alive"/><cell state="dead"/><cell state="dead"/><cell state="dead"/><cell state="dead"/><cell state="dead"/><cell state="dead"/><cell state="alive"/><cell state="alive"/><cell state="dead"/><cell state="dead"/><cell state="dead"/><cell state="dead"/><cell state="dead"/><cell state="dead"/><cell state="dead"/><cell state="dead"/><cell state="dead"/><cell state="dead"/><cell state="dead"/><cell state="dead"/><cell state="dead"/><cell state="dead"/><cell state="dead"/><cell state="dead"/><cell state="dead"/>
        <cell state="dead"/><cell state="dead"/><cell state="dead"/><cell state="dead"/><cell state="dead"/><cell state="dead"/><cell state="dead"/><cell state="dead"/><cell state="dead"/><cell state="dead"/><cell state="dead"/><cell state="dead"/><cell state="dead"/><cell state="dead"/><cell state="dead"/><cell state="dead"/><cell state="dead"/><cell state="dead"/><cell state="dead"/><cell state="dead"/><cell state="dead"/><cell state="dead"/><cell state="dead"/><cell state="dead"/><cell state="dead"/><cell state="dead"/><cell state="dead"/><cell state="dead"/><cell state="dead"/><cell state="dead"/><cell state="alive"/><cell state="alive"/><cell state="alive"/><cell state="alive"/><cell state="alive"/><cell state="dead"/><cell state="dead"/><cell state="dead"/><cell state="dead"/><cell state="dead"/><cell state="dead"/><cell state="dead"/><cell state="dead"/><cell state="dead"/><cell state="dead"/><cell state="dead"/><cell state="dead"/><cell state="dead"/><cell state="dead"/><cell state="dead"/><cell state="dead"/><cell state="dead"/><cell state="dead"/><cell state="dead"/><cell state="dead"/><cell state="dead"/><cell state="dead"/><cell state="dead"/><cell state="dead"/><cell state="dead"/>

        <!-- Empty rows for centering -->
        <cell state="dead"/><cell state="dead"/><cell state="dead"/><cell state="dead"/><cell state="dead"/><cell state="dead"/><cell state="dead"/><cell state="dead"/><cell state="dead"/><cell state="dead"/><cell state="dead"/><cell state="dead"/><cell state="dead"/><cell state="dead"/><cell state="dead"/><cell state="dead"/><cell state="dead"/><cell state="dead"/><cell state="dead"/><cell state="dead"/><cell state="dead"/><cell state="dead"/><cell state="dead"/><cell state="dead"/><cell state="dead"/><cell state="dead"/><cell state="dead"/><cell state="dead"/><cell state="dead"/><cell state="dead"/><cell state="dead"/><cell state="dead"/><cell state="dead"/><cell state="dead"/><cell state="dead"/><cell state="dead"/><cell state="dead"/><cell state="dead"/><cell state="dead"/><cell state="dead"/><cell state="dead"/><cell state="dead"/><cell state="dead"/><cell state="dead"/><cell state="dead"/><cell state="dead"/><cell state="dead"/><cell state="dead"/><cell state="dead"/><cell state="dead"/><cell state="dead"/><cell state="dead"/><cell state="dead"/><cell state="dead"/><cell state="dead"/><cell state="dead"/><cell state="dead"/><cell state="dead"/><cell state="dead"/><cell state="dead"/>
        <cell state="dead"/><cell state="dead"/><cell state="dead"/><cell state="dead"/><cell state="dead"/><cell state="dead"/><cell state="dead"/><cell state="dead"/><cell state="dead"/><cell state="dead"/><cell state="dead"/><cell state="dead"/><cell state="dead"/><cell state="dead"/><cell state="dead"/><cell state="dead"/><cell state="dead"/><cell state="dead"/><cell state="dead"/><cell state="dead"/><cell state="dead"/><cell state="dead"/><cell state="dead"/><cell state="dead"/><cell state="dead"/><cell state="dead"/><cell state="dead"/><cell state="dead"/><cell state="dead"/><cell state="dead"/><cell state="dead"/><cell state="dead"/><cell state="dead"/><cell state="dead"/><cell state="dead"/><cell state="dead"/><cell state="dead"/><cell state="dead"/><cell state="dead"/><cell state="dead"/><cell state="dead"/><cell state="dead"/><cell state="dead"/><cell state="dead"/><cell state="dead"/><cell state="dead"/><cell state="dead"/><cell state="dead"/><cell state="dead"/><cell state="dead"/><cell state="dead"/><cell state="dead"/><cell state="dead"/><cell state="dead"/><cell state="dead"/><cell state="dead"/><cell state="dead"/><cell state="dead"/><cell state="dead"/><cell state="dead"/>
        <cell state="dead"/><cell state="dead"/><cell state="dead"/><cell state="dead"/><cell state="dead"/><cell state="dead"/><cell state="dead"/><cell state="dead"/><cell state="dead"/><cell state="dead"/><cell state="dead"/><cell state="dead"/><cell state="dead"/><cell state="dead"/><cell state="dead"/><cell state="dead"/><cell state="dead"/><cell state="dead"/><cell state="dead"/><cell state="dead"/><cell state="dead"/><cell state="dead"/><cell state="dead"/><cell state="dead"/><cell state="dead"/><cell state="dead"/><cell state="dead"/><cell state="dead"/><cell state="dead"/><cell state="dead"/><cell state="dead"/><cell state="dead"/><cell state="dead"/><cell state="dead"/><cell state="dead"/><cell state="dead"/><cell state="dead"/><cell state="dead"/><cell state="dead"/><cell state="dead"/><cell state="dead"/><cell state="dead"/><cell state="dead"/><cell state="dead"/><cell state="dead"/><cell state="dead"/><cell state="dead"/><cell state="dead"/><cell state="dead"/><cell state="dead"/><cell state="dead"/><cell state="dead"/><cell state="dead"/><cell state="dead"/><cell state="dead"/><cell state="dead"/><cell state="dead"/><cell state="dead"/><cell state="dead"/><cell state="dead"/>
        <cell state="dead"/><cell state="dead"/><cell state="dead"/><cell state="dead"/><cell state="dead"/><cell state="dead"/><cell state="dead"/><cell state="dead"/><cell state="dead"/><cell state="dead"/><cell state="dead"/><cell state="dead"/><cell state="dead"/><cell state="dead"/><cell state="dead"/><cell state="dead"/><cell state="dead"/><cell state="dead"/><cell state="dead"/><cell state="dead"/><cell state="dead"/><cell state="dead"/><cell state="dead"/><cell state="dead"/><cell state="dead"/><cell state="dead"/><cell state="dead"/><cell state="dead"/><cell state="dead"/><cell state="dead"/><cell state="dead"/><cell state="dead"/><cell state="dead"/><cell state="dead"/><cell state="dead"/><cell state="dead"/><cell state="dead"/><cell state="dead"/><cell state="dead"/><cell state="dead"/><cell state="dead"/><cell state="dead"/><cell state="dead"/><cell state="dead"/><cell state="dead"/><cell state="dead"/><cell state="dead"/><cell state="dead"/><cell state="dead"/><cell state="dead"/><cell state="dead"/><cell state="dead"/><cell state="dead"/><cell state="dead"/><cell state="dead"/><cell state="dead"/><cell state="dead"/><cell state="dead"/><cell state="dead"/><cell state="dead"/>
        <cell state="dead"/><cell state="dead"/><cell state="dead"/><cell state="dead"/><cell state="dead"/><cell state="dead"/><cell state="dead"/><cell state="dead"/><cell state="dead"/><cell state="dead"/><cell state="dead"/><cell state="dead"/><cell state="dead"/><cell state="dead"/><cell state="dead"/><cell state="dead"/><cell state="dead"/><cell state="dead"/><cell state="dead"/><cell state="dead"/><cell state="dead"/><cell state="dead"/><cell state="dead"/><cell state="dead"/><cell state="dead"/><cell state="dead"/><cell state="dead"/><cell state="dead"/><cell state="dead"/><cell state="dead"/><cell state="dead"/><cell state="dead"/><cell state="dead"/><cell state="dead"/><cell state="dead"/><cell state="dead"/><cell state="dead"/><cell state="dead"/><cell state="dead"/><cell state="dead"/><cell state="dead"/><cell state="dead"/><cell state="dead"/><cell state="dead"/><cell state="dead"/><cell state="dead"/><cell state="dead"/><cell state="dead"/><cell state="dead"/><cell state="dead"/><cell state="dead"/><cell state="dead"/><cell state="dead"/><cell state="dead"/><cell state="dead"/><cell state="dead"/><cell state="dead"/><cell state="dead"/><cell state="dead"/><cell state="dead"/>
        <cell state="dead"/><cell state="dead"/><cell state="dead"/><cell state="dead"/><cell state="dead"/><cell state="dead"/><cell state="dead"/><cell state="dead"/><cell state="dead"/><cell state="dead"/><cell state="dead"/><cell state="dead"/><cell state="dead"/><cell state="dead"/><cell state="dead"/><cell state="dead"/><cell state="dead"/><cell state="dead"/><cell state="dead"/><cell state="dead"/><cell state="dead"/><cell state="dead"/><cell state="dead"/><cell state="dead"/><cell state="dead"/><cell state="dead"/><cell state="dead"/><cell state="dead"/><cell state="dead"/><cell state="dead"/><cell state="dead"/><cell state="dead"/><cell state="dead"/><cell state="dead"/><cell state="dead"/><cell state="dead"/><cell state="dead"/><cell state="dead"/><cell state="dead"/><cell state="dead"/><cell state="dead"/><cell state="dead"/><cell state="dead"/><cell state="dead"/><cell state="dead"/><cell state="dead"/><cell state="dead"/><cell state="dead"/><cell state="dead"/><cell state="dead"/><cell state="dead"/><cell state="dead"/><cell state="dead"/><cell state="dead"/><cell state="dead"/><cell state="dead"/><cell state="dead"/><cell state="dead"/><cell state="dead"/><cell state="dead"/>
        <cell state="dead"/><cell state="dead"/><cell state="dead"/><cell state="dead"/><cell state="dead"/><cell state="dead"/><cell state="dead"/><cell state="dead"/><cell state="dead"/><cell state="dead"/><cell state="dead"/><cell state="dead"/><cell state="dead"/><cell state="dead"/><cell state="dead"/><cell state="dead"/><cell state="dead"/><cell state="dead"/><cell state="dead"/><cell state="dead"/><cell state="dead"/><cell state="dead"/><cell state="dead"/><cell state="dead"/><cell state="dead"/><cell state="dead"/><cell state="dead"/><cell state="dead"/><cell state="dead"/><cell state="dead"/><cell state="dead"/><cell state="dead"/><cell state="dead"/><cell state="dead"/><cell state="dead"/><cell state="dead"/><cell state="dead"/><cell state="dead"/><cell state="dead"/><cell state="dead"/><cell state="dead"/><cell state="dead"/><cell state="dead"/><cell state="dead"/><cell state="dead"/><cell state="dead"/><cell state="dead"/><cell state="dead"/><cell state="dead"/><cell state="dead"/><cell state="dead"/><cell state="dead"/><cell state="dead"/><cell state="dead"/><cell state="dead"/><cell state="dead"/><cell state="dead"/><cell state="dead"/><cell state="dead"/><cell state="dead"/>
        <cell state="dead"/><cell state="dead"/><cell state="dead"/><cell state="dead"/><cell state="dead"/><cell state="dead"/><cell state="dead"/><cell state="dead"/><cell state="dead"/><cell state="dead"/><cell state="dead"/><cell state="dead"/><cell state="dead"/><cell state="dead"/><cell state="dead"/><cell state="dead"/><cell state="dead"/><cell state="dead"/><cell state="dead"/><cell state="dead"/><cell state="dead"/><cell state="dead"/><cell state="dead"/><cell state="dead"/><cell state="dead"/><cell state="dead"/><cell state="dead"/><cell state="dead"/><cell state="dead"/><cell state="dead"/><cell state="dead"/><cell state="dead"/><cell state="dead"/><cell state="dead"/><cell state="dead"/><cell state="dead"/><cell state="dead"/><cell state="dead"/><cell state="dead"/><cell state="dead"/><cell state="dead"/><cell state="dead"/><cell state="dead"/><cell state="dead"/><cell state="dead"/><cell state="dead"/><cell state="dead"/><cell state="dead"/><cell state="dead"/><cell state="dead"/><cell state="dead"/><cell state="dead"/><cell state="dead"/><cell state="dead"/><cell state="dead"/><cell state="dead"/><cell state="dead"/><cell state="dead"/><cell state="dead"/><cell state="dead"/>
        <cell state="dead"/><cell state="dead"/><cell state="dead"/><cell state="dead"/><cell state="dead"/><cell state="dead"/><cell state="dead"/><cell state="dead"/><cell state="dead"/><cell state="dead"/><cell state="dead"/><cell state="dead"/><cell state="dead"/><cell state="dead"/><cell state="dead"/><cell state="dead"/><cell state="dead"/><cell state="dead"/><cell state="dead"/><cell state="dead"/><cell state="dead"/><cell state="dead"/><cell state="dead"/><cell state="dead"/><cell state="dead"/><cell state="dead"/><cell state="dead"/><cell state="dead"/><cell state="dead"/><cell state="dead"/><cell state="dead"/><cell state="dead"/><cell state="dead"/><cell state="dead"/><cell state="dead"/><cell state="dead"/><cell state="dead"/><cell state="dead"/><cell state="dead"/><cell state="dead"/><cell state="dead"/><cell state="dead"/><cell state="dead"/><cell state="dead"/><cell state="dead"/><cell state="dead"/><cell state="dead"/><cell state="dead"/><cell state="dead"/><cell state="dead"/><cell state="dead"/><cell state="dead"/><cell state="dead"/><cell state="dead"/><cell state="dead"/><cell state="dead"/><cell state="dead"/><cell state="dead"/><cell state="dead"/><cell state="dead"/>
        <cell state="dead"/><cell state="dead"/><cell state="dead"/><cell state="dead"/><cell state="dead"/><cell state="dead"/><cell state="dead"/><cell state="dead"/><cell state="dead"/><cell state="dead"/><cell state="dead"/><cell state="dead"/><cell state="dead"/><cell state="dead"/><cell state="dead"/><cell state="dead"/><cell state="dead"/><cell state="dead"/><cell state="dead"/><cell state="dead"/><cell state="dead"/><cell state="dead"/><cell state="dead"/><cell state="dead"/><cell state="dead"/><cell state="dead"/><cell state="dead"/><cell state="dead"/><cell state="dead"/><cell state="dead"/><cell state="dead"/><cell state="dead"/><cell state="dead"/><cell state="dead"/><cell state="dead"/><cell state="dead"/><cell state="dead"/><cell state="dead"/><cell state="dead"/><cell state="dead"/><cell state="dead"/><cell state="dead"/><cell state="dead"/><cell state="dead"/><cell state="dead"/><cell state="dead"/><cell state="dead"/><cell state="dead"/><cell state="dead"/><cell state="dead"/><cell state="dead"/><cell state="dead"/><cell state="dead"/><cell state="dead"/><cell state="dead"/><cell state="dead"/><cell state="dead"/><cell state="dead"/><cell state="dead"/><cell state="dead"/>
        <cell state="dead"/><cell state="dead"/><cell state="dead"/><cell state="dead"/><cell state="dead"/><cell state="dead"/><cell state="dead"/><cell state="dead"/><cell state="dead"/><cell state="dead"/><cell state="dead"/><cell state="dead"/><cell state="dead"/><cell state="dead"/><cell state="dead"/><cell state="dead"/><cell state="dead"/><cell state="dead"/><cell state="dead"/><cell state="dead"/><cell state="dead"/><cell state="dead"/><cell state="dead"/><cell state="dead"/><cell state="dead"/><cell state="dead"/><cell state="dead"/><cell state="dead"/><cell state="dead"/><cell state="dead"/><cell state="dead"/><cell state="dead"/><cell state="dead"/><cell state="dead"/><cell state="dead"/><cell state="dead"/><cell state="dead"/><cell state="dead"/><cell state="dead"/><cell state="dead"/><cell state="dead"/><cell state="dead"/><cell state="dead"/><cell state="dead"/><cell state="dead"/><cell state="dead"/><cell state="dead"/><cell state="dead"/><cell state="dead"/><cell state="dead"/><cell state="dead"/><cell state="dead"/><cell state="dead"/><cell state="dead"/><cell state="dead"/><cell state="dead"/><cell state="dead"/><cell state="dead"/><cell state="dead"/><cell state="dead"/>
        <cell state="dead"/><cell state="dead"/><cell state="dead"/><cell state="dead"/><cell state="dead"/><cell state="dead"/><cell state="dead"/><cell state="dead"/><cell state="dead"/><cell state="dead"/><cell state="dead"/><cell state="dead"/><cell state="dead"/><cell state="dead"/><cell state="dead"/><cell state="dead"/><cell state="dead"/><cell state="dead"/><cell state="dead"/><cell state="dead"/><cell state="dead"/><cell state="dead"/><cell state="dead"/><cell state="dead"/><cell state="dead"/><cell state="dead"/><cell state="dead"/><cell state="dead"/><cell state="dead"/><cell state="dead"/><cell state="dead"/><cell state="dead"/><cell state="dead"/><cell state="dead"/><cell state="dead"/><cell state="dead"/><cell state="dead"/><cell state="dead"/><cell state="dead"/><cell state="dead"/><cell state="dead"/><cell state="dead"/><cell state="dead"/><cell state="dead"/><cell state="dead"/><cell state="dead"/><cell state="dead"/><cell state="dead"/><cell state="dead"/><cell state="dead"/><cell state="dead"/><cell state="dead"/><cell state="dead"/><cell state="dead"/><cell state="dead"/><cell state="dead"/><cell state="dead"/><cell state="dead"/><cell state="dead"/><cell state="dead"/>
        <cell state="dead"/><cell state="dead"/><cell state="dead"/><cell state="dead"/><cell state="dead"/><cell state="dead"/><cell state="dead"/><cell state="dead"/><cell state="dead"/><cell state="dead"/><cell state="dead"/><cell state="dead"/><cell state="dead"/><cell state="dead"/><cell state="dead"/><cell state="dead"/><cell state="dead"/><cell state="dead"/><cell state="dead"/><cell state="dead"/><cell state="dead"/><cell state="dead"/><cell state="dead"/><cell state="dead"/><cell state="dead"/><cell state="dead"/><cell state="dead"/><cell state="dead"/><cell state="dead"/><cell state="dead"/><cell state="dead"/><cell state="dead"/><cell state="dead"/><cell state="dead"/><cell state="dead"/><cell state="dead"/><cell state="dead"/><cell state="dead"/><cell state="dead"/><cell state="dead"/><cell state="dead"/><cell state="dead"/><cell state="dead"/><cell state="dead"/><cell state="dead"/><cell state="dead"/><cell state="dead"/><cell state="dead"/><cell state="dead"/><cell state="dead"/><cell state="dead"/><cell state="dead"/><cell state="dead"/><cell state="dead"/><cell state="dead"/><cell state="dead"/><cell state="dead"/><cell state="dead"/><cell state="dead"/><cell state="dead"/>
        <cell state="dead"/><cell state="dead"/><cell state="dead"/><cell state="dead"/><cell state="dead"/><cell state="dead"/><cell state="dead"/><cell state="dead"/><cell state="dead"/><cell state="dead"/><cell state="dead"/><cell state="dead"/><cell state="dead"/><cell state="dead"/><cell state="dead"/><cell state="dead"/><cell state="dead"/><cell state="dead"/><cell state="dead"/><cell state="dead"/><cell state="dead"/><cell state="dead"/><cell state="dead"/><cell state="dead"/><cell state="dead"/><cell state="dead"/><cell state="dead"/><cell state="dead"/><cell state="dead"/><cell state="dead"/><cell state="dead"/><cell state="dead"/><cell state="dead"/><cell state="dead"/><cell state="dead"/><cell state="dead"/><cell state="dead"/><cell state="dead"/><cell state="dead"/><cell state="dead"/><cell state="dead"/><cell state="dead"/><cell state="dead"/><cell state="dead"/><cell state="dead"/><cell state="dead"/><cell state="dead"/><cell state="dead"/><cell state="dead"/><cell state="dead"/><cell state="dead"/><cell state="dead"/><cell state="dead"/><cell state="dead"/><cell state="dead"/><cell state="dead"/><cell state="dead"/><cell state="dead"/><cell state="dead"/><cell state="dead"/>
        <cell state="dead"/><cell state="dead"/><cell state="dead"/><cell state="dead"/><cell state="dead"/><cell state="dead"/><cell state="dead"/><cell state="dead"/><cell state="dead"/><cell state="dead"/><cell state="dead"/><cell state="dead"/><cell state="dead"/><cell state="dead"/><cell state="dead"/><cell state="dead"/><cell state="dead"/><cell state="dead"/><cell state="dead"/><cell state="dead"/><cell state="dead"/><cell state="dead"/><cell state="dead"/><cell state="dead"/><cell state="dead"/><cell state="dead"/><cell state="dead"/><cell state="dead"/><cell state="dead"/><cell state="dead"/><cell state="dead"/><cell state="dead"/><cell state="dead"/><cell state="dead"/><cell state="dead"/><cell state="dead"/><cell state="dead"/><cell state="dead"/><cell state="dead"/><cell state="dead"/><cell state="dead"/><cell state="dead"/><cell state="dead"/><cell state="dead"/><cell state="dead"/><cell state="dead"/><cell state="dead"/><cell state="dead"/><cell state="dead"/><cell state="dead"/><cell state="dead"/><cell state="dead"/><cell state="dead"/><cell state="dead"/><cell state="dead"/><cell state="dead"/><cell state="dead"/><cell state="dead"/><cell state="dead"/><cell state="dead"/>
        <cell state="dead"/><cell state="dead"/><cell state="dead"/><cell state="dead"/><cell state="dead"/><cell state="dead"/><cell state="dead"/><cell state="dead"/><cell state="dead"/><cell state="dead"/><cell state="dead"/><cell state="dead"/><cell state="dead"/><cell state="dead"/><cell state="dead"/><cell state="dead"/><cell state="dead"/><cell state="dead"/><cell state="dead"/><cell state="dead"/><cell state="dead"/><cell state="dead"/><cell state="dead"/><cell state="dead"/><cell state="dead"/><cell state="dead"/><cell state="dead"/><cell state="dead"/><cell state="dead"/><cell state="dead"/><cell state="dead"/><cell state="dead"/><cell state="dead"/><cell state="dead"/><cell state="dead"/><cell state="dead"/><cell state="dead"/><cell state="dead"/><cell state="dead"/><cell state="dead"/><cell state="dead"/><cell state="dead"/><cell state="dead"/><cell state="dead"/><cell state="dead"/><cell state="dead"/><cell state="dead"/><cell state="dead"/><cell state="dead"/><cell state="dead"/><cell state="dead"/><cell state="dead"/><cell state="dead"/><cell state="dead"/><cell state="dead"/><cell state="dead"/><cell state="dead"/><cell state="dead"/><cell state="dead"/><cell state="dead"/>
        <cell state="dead"/><cell state="dead"/><cell state="dead"/><cell state="dead"/><cell state="dead"/><cell state="dead"/><cell state="dead"/><cell state="dead"/><cell state="dead"/><cell state="dead"/><cell state="dead"/><cell state="dead"/><cell state="dead"/><cell state="dead"/><cell state="dead"/><cell state="dead"/><cell state="dead"/><cell state="dead"/><cell state="dead"/><cell state="dead"/><cell state="dead"/><cell state="dead"/><cell state="dead"/><cell state="dead"/><cell state="dead"/><cell state="dead"/><cell state="dead"/><cell state="dead"/><cell state="dead"/><cell state="dead"/><cell state="dead"/><cell state="dead"/><cell state="dead"/><cell state="dead"/><cell state="dead"/><cell state="dead"/><cell state="dead"/><cell state="dead"/><cell state="dead"/><cell state="dead"/><cell state="dead"/><cell state="dead"/><cell state="dead"/><cell state="dead"/><cell state="dead"/><cell state="dead"/><cell state="dead"/><cell state="dead"/><cell state="dead"/><cell state="dead"/><cell state="dead"/><cell state="dead"/><cell state="dead"/><cell state="dead"/><cell state="dead"/><cell state="dead"/><cell state="dead"/><cell state="dead"/><cell state="dead"/><cell state="dead"/>
        <cell state="dead"/><cell state="dead"/><cell state="dead"/><cell state="dead"/><cell state="dead"/><cell state="dead"/><cell state="dead"/><cell state="dead"/><cell state="dead"/><cell state="dead"/><cell state="dead"/><cell state="dead"/><cell state="dead"/><cell state="dead"/><cell state="dead"/><cell state="dead"/><cell state="dead"/><cell state="dead"/><cell state="dead"/><cell state="dead"/><cell state="dead"/><cell state="dead"/><cell state="dead"/><cell state="dead"/><cell state="dead"/><cell state="dead"/><cell state="dead"/><cell state="dead"/><cell state="dead"/><cell state="dead"/><cell state="dead"/><cell state="dead"/><cell state="dead"/><cell state="dead"/><cell state="dead"/><cell state="dead"/><cell state="dead"/><cell state="dead"/><cell state="dead"/><cell state="dead"/><cell state="dead"/><cell state="dead"/><cell state="dead"/><cell state="dead"/><cell state="dead"/><cell state="dead"/><cell state="dead"/><cell state="dead"/><cell state="dead"/><cell state="dead"/><cell state="dead"/><cell state="dead"/><cell state="dead"/><cell state="dead"/><cell state="dead"/><cell state="dead"/><cell state="dead"/><cell state="dead"/><cell state="dead"/><cell state="dead"/>
    </grid>

    <parameters>
        <!-- I think this is supposed to slide to the side. -->
    </parameters>
</simulation>
